miner/__init__.py
miner/__main__.py
miner/app.py
miner/cli.py
miner/cli_adapters.py
miner/data.py
miner/friends.py
miner/people.py
miner/person.py
miner/profile_information.py
miner/trash.py
miner/message/conversation.py
miner/message/conversation_stats.py
miner/message/conversations.py
miner/message/messaging_analyzer.py
miner/utils/command.py
miner/utils/const.py
miner/utils/decorators.py
miner/utils/period_manager.py
miner/utils/utils.py
miner/visualizer/adapters.py
miner/visualizer/plotter.py
miner/visualizer/table_creator.py
facebook_data_miner-0.1.0.dist-info/LICENSE
facebook_data_miner-0.1.0.dist-info/METADATA
facebook_data_miner-0.1.0.dist-info/WHEEL
facebook_data_miner-0.1.0.dist-info/top_level.txt
facebook_data_miner-0.1.0.dist-info/RECORD
