Metadata-Version: 2.1
Name: facebook-data-miner
Version: 0.1.0
Summary: An object-oriented approach to mining personal Facebook data.
Home-page: https://github.com/tardigrde/facebook-data-miner
Author: Levente Csőke
Author-email: leventec3@gmail.com
License: GPL-3.0
Keywords: facebook-data,facebook-data-miner,facebook-data-analyzer
Platform: UNKNOWN
Classifier: Intended Audience :: Developers
Classifier: License :: OSI Approved :: GNU General Public License v3 (GPLv3)
Classifier: Operating System :: OS Independent
Classifier: Programming Language :: Python :: 3.8
Classifier: Topic :: Software Development :: Libraries :: Python Modules
Classifier: Development Status :: 3 - Alpha
Requires-Python: >=3.8
Requires-Dist: setuptools
